smart_steganography_lib/__init__.py
smart_steganography_lib/steganography_tool.py
smart_steganography_lib-0.1.1.dist-info/LICENSE
smart_steganography_lib-0.1.1.dist-info/METADATA
smart_steganography_lib-0.1.1.dist-info/WHEEL
smart_steganography_lib-0.1.1.dist-info/top_level.txt
smart_steganography_lib-0.1.1.dist-info/RECORD
