Metadata-Version: 2.1
Name: smart_steganography_lib
Version: 0.1.1
Summary: 'Smart Steganography Library is a cross-platform library that allows you to hide and extract text messages in images.'
Home-page: https://github.com/smartlegionlab
Author: A.A. Suvorov
Author-email: smartlegiondev@gmail.com
License: BSD 3-Clause License
Project-URL: Documentation, https://github.com/smartlegionlab/smart_steganography_lib/blob/master/README.md
Project-URL: Release notes, https://github.com/smartlegionlab/smart_steganography_lib/releases
Keywords: smart_steganography_lib,steganography,smartlegionlab
Classifier: Development Status :: 5 - Production/Stable
Classifier: Environment :: Console
Classifier: Intended Audience :: End Users/Desktop
Classifier: Intended Audience :: System Administrators
Classifier: License :: OSI Approved :: BSD License
Classifier: Natural Language :: English
Classifier: Operating System :: OS Independent
Classifier: Operating System :: Microsoft :: Windows
Classifier: Operating System :: POSIX :: Linux
Classifier: Programming Language :: Python :: 3 :: Only
Classifier: Topic :: Software Development :: Libraries :: Python Modules
Classifier: Topic :: Utilities
Requires-Python: >=3.6
License-File: LICENSE
Requires-Dist: pillow==11.0.0
Requires-Dist: smarttextdecorator==0.1.2
